aiozyre/__init__.py
aiozyre/exceptions.py
aiozyre/futures.py
aiozyre/messages.py
aiozyre/node.py
aiozyre/nodeactor.cpython-312-darwin.so
aiozyre/nodeactor.pxd
aiozyre/nodeactor.pyx
aiozyre/nodeconfig.py
aiozyre/signals.cpython-312-darwin.so
aiozyre/signals.pxd
aiozyre/signals.pyx
aiozyre/util.cpython-312-darwin.so
aiozyre/util.pxd
aiozyre/util.pyx
aiozyre/zyre.pxd
xaiozyre-1.1.6.data/data/LICENSE
xaiozyre-1.1.6.data/data/README.md
xaiozyre-1.1.6.dist-info/LICENSE
xaiozyre-1.1.6.dist-info/METADATA
xaiozyre-1.1.6.dist-info/WHEEL
xaiozyre-1.1.6.dist-info/top_level.txt
xaiozyre-1.1.6.dist-info/RECORD
