Metadata-Version: 2.1
Name: xaiozyre
Version: 1.1.6
Summary: asyncio-friendly Python bindings for Zyre
Author: Dennis Hilmar
Author-email: dhk@xtel.dk
Classifier: Environment :: Console
Classifier: Intended Audience :: Developers
Classifier: License :: OSI Approved :: BSD License
Classifier: Operating System :: MacOS :: MacOS X
Classifier: Programming Language :: Python :: 3
Classifier: Programming Language :: Python :: 3
Classifier: Topic :: System :: Networking
Classifier: Framework :: AsyncIO
License-File: LICENSE
Provides-Extra: dev
Requires-Dist: blessed ; extra == 'dev'
Requires-Dist: aioconsole ; extra == 'dev'
